trice/__init__.py
trice/example.py
trice-0.0.0.dist-info/METADATA
trice-0.0.0.dist-info/WHEEL
trice-0.0.0.dist-info/licenses/LICENSE
trice-0.0.0.dist-info/RECORD
